{
    "DM_4CRSOL": true,
    "DM_5DRIB": true,
    "DM_AACALD": true,
    "DM_AMOB": true,
    "DM_MTHTHF": true,
    "DM_OXAM": true,
    "Ec_biomass_iJO1366_WT_53p95M": true,
    "EX_12ppd_DASH_R_LPAREN_e_RPAREN_": true,
    "EX_12ppd_DASH_S_LPAREN_e_RPAREN_": true,
    "EX_14glucan_LPAREN_e_RPAREN_": true,
    "EX_15dap_LPAREN_e_RPAREN_": true,
    "EX_23camp_LPAREN_e_RPAREN_": true,
    "EX_23ccmp_LPAREN_e_RPAREN_": true,
    "EX_23cgmp_LPAREN_e_RPAREN_": true,
    "EX_23cump_LPAREN_e_RPAREN_": true,
    "EX_23dappa_LPAREN_e_RPAREN_": true,
    "EX_26dap_DASH_M_LPAREN_e_RPAREN_": true,
    "EX_2ddglcn_LPAREN_e_RPAREN_": true,
    "EX_34dhpac_LPAREN_e_RPAREN_": true,
    "EX_3amp_LPAREN_e_RPAREN_": true,
    "EX_3cmp_LPAREN_e_RPAREN_": true,
    "EX_3gmp_LPAREN_e_RPAREN_": true,
    "EX_3hcinnm_LPAREN_e_RPAREN_": true,
    "EX_3hpp_LPAREN_e_RPAREN_": true,
    "EX_3hpppn_LPAREN_e_RPAREN_": true,
    "EX_3ump_LPAREN_e_RPAREN_": true,
    "EX_4abut_LPAREN_e_RPAREN_": true,
    "EX_4hoxpacd_LPAREN_e_RPAREN_": true,
    "EX_5dglcn_LPAREN_e_RPAREN_": true,
    "EX_5mtr_LPAREN_e_RPAREN_": false,
    "EX_LalaDglu_LPAREN_e_RPAREN_": true,
    "EX_LalaDgluMdap_LPAREN_e_RPAREN_": true,
    "EX_LalaDgluMdapDala_LPAREN_e_RPAREN_": true,
    "EX_LalaLglu_LPAREN_e_RPAREN_": true,
    "EX_ac_LPAREN_e_RPAREN_": true,
    "EX_acac_LPAREN_e_RPAREN_": true,
    "EX_acald_LPAREN_e_RPAREN_": true,
    "EX_acgal_LPAREN_e_RPAREN_": true,
    "EX_acgal1p_LPAREN_e_RPAREN_": true,
    "EX_acgam_LPAREN_e_RPAREN_": true,
    "EX_acgam1p_LPAREN_e_RPAREN_": true,
    "EX_acmana_LPAREN_e_RPAREN_": true,
    "EX_acmum_LPAREN_e_RPAREN_": true,
    "EX_acnam_LPAREN_e_RPAREN_": true,
    "EX_acolipa_LPAREN_e_RPAREN_": true,
    "EX_acser_LPAREN_e_RPAREN_": true,
    "EX_ade_LPAREN_e_RPAREN_": true,
    "EX_adn_LPAREN_e_RPAREN_": true,
    "EX_adocbl_LPAREN_e_RPAREN_": true,
    "EX_ag_LPAREN_e_RPAREN_": true,
    "EX_agm_LPAREN_e_RPAREN_": true,
    "EX_akg_LPAREN_e_RPAREN_": true,
    "EX_ala_DASH_B_LPAREN_e_RPAREN_": true,
    "EX_ala_DASH_D_LPAREN_e_RPAREN_": true,
    "EX_ala_DASH_L_LPAREN_e_RPAREN_": true,
    "EX_alaala_LPAREN_e_RPAREN_": true,
    "EX_all_DASH_D_LPAREN_e_RPAREN_": true,
    "EX_alltn_LPAREN_e_RPAREN_": true,
    "EX_amp_LPAREN_e_RPAREN_": true,
    "EX_anhgm_LPAREN_e_RPAREN_": true,
    "EX_arab_DASH_L_LPAREN_e_RPAREN_": true,
    "EX_arbt_LPAREN_e_RPAREN_": true,
    "EX_arbtn_LPAREN_e_RPAREN_": true,
    "EX_arbtn_DASH_fe3_LPAREN_e_RPAREN_": true,
    "EX_arg_DASH_L_LPAREN_e_RPAREN_": true,
    "EX_ascb_DASH_L_LPAREN_e_RPAREN_": true,
    "EX_asn_DASH_L_LPAREN_e_RPAREN_": true,
    "EX_aso3_LPAREN_e_RPAREN_": true,
    "EX_asp_DASH_L_LPAREN_e_RPAREN_": true,
    "EX_btn_LPAREN_e_RPAREN_": true,
    "EX_but_LPAREN_e_RPAREN_": true,
    "EX_butso3_LPAREN_e_RPAREN_": true,
    "EX_ca2_LPAREN_e_RPAREN_": true,
    "EX_cbi_LPAREN_e_RPAREN_": true,
    "EX_cbl1_LPAREN_e_RPAREN_": true,
    "EX_cd2_LPAREN_e_RPAREN_": true,
    "EX_cgly_LPAREN_e_RPAREN_": true,
    "EX_chol_LPAREN_e_RPAREN_": true,
    "EX_chtbs_LPAREN_e_RPAREN_": true,
    "EX_cit_LPAREN_e_RPAREN_": true,
    "EX_cl_LPAREN_e_RPAREN_": true,
    "EX_cm_LPAREN_e_RPAREN_": true,
    "EX_cmp_LPAREN_e_RPAREN_": true,
    "EX_co2_LPAREN_e_RPAREN_": false,
    "EX_cobalt2_LPAREN_e_RPAREN_": true,
    "EX_colipa_LPAREN_e_RPAREN_": true,
    "EX_colipap_LPAREN_e_RPAREN_": true,
    "EX_cpgn_LPAREN_e_RPAREN_": true,
    "EX_cpgn_DASH_un_LPAREN_e_RPAREN_": true,
    "EX_crn_LPAREN_e_RPAREN_": true,
    "EX_crn_DASH_D_LPAREN_e_RPAREN_": true,
    "EX_csn_LPAREN_e_RPAREN_": true,
    "EX_cu_LPAREN_e_RPAREN_": true,
    "EX_cu2_LPAREN_e_RPAREN_": true,
    "EX_cyan_LPAREN_e_RPAREN_": true,
    "EX_cynt_LPAREN_e_RPAREN_": true,
    "EX_cys_DASH_D_LPAREN_e_RPAREN_": true,
    "EX_cys_DASH_L_LPAREN_e_RPAREN_": true,
    "EX_cytd_LPAREN_e_RPAREN_": true,
    "EX_dad_DASH_2_LPAREN_e_RPAREN_": true,
    "EX_damp_LPAREN_e_RPAREN_": true,
    "EX_dca_LPAREN_e_RPAREN_": true,
    "EX_dcmp_LPAREN_e_RPAREN_": true,
    "EX_dcyt_LPAREN_e_RPAREN_": true,
    "EX_ddca_LPAREN_e_RPAREN_": true,
    "EX_dgmp_LPAREN_e_RPAREN_": true,
    "EX_dgsn_LPAREN_e_RPAREN_": true,
    "EX_dha_LPAREN_e_RPAREN_": true,
    "EX_dimp_LPAREN_e_RPAREN_": true,
    "EX_din_LPAREN_e_RPAREN_": true,
    "EX_dms_LPAREN_e_RPAREN_": true,
    "EX_dmso_LPAREN_e_RPAREN_": true,
    "EX_dopa_LPAREN_e_RPAREN_": true,
    "EX_doxrbcn_LPAREN_e_RPAREN_": true,
    "EX_dtmp_LPAREN_e_RPAREN_": true,
    "EX_dump_LPAREN_e_RPAREN_": true,
    "EX_duri_LPAREN_e_RPAREN_": true,
    "EX_eca4colipa_LPAREN_e_RPAREN_": true,
    "EX_enlipa_LPAREN_e_RPAREN_": true,
    "EX_enter_LPAREN_e_RPAREN_": true,
    "EX_etha_LPAREN_e_RPAREN_": true,
    "EX_ethso3_LPAREN_e_RPAREN_": true,
    "EX_etoh_LPAREN_e_RPAREN_": true,
    "EX_f6p_LPAREN_e_RPAREN_": true,
    "EX_fald_LPAREN_e_RPAREN_": true,
    "EX_fe2_LPAREN_e_RPAREN_": true,
    "EX_fe3_LPAREN_e_RPAREN_": true,
    "EX_fe3dcit_LPAREN_e_RPAREN_": true,
    "EX_fe3dhbzs_LPAREN_e_RPAREN_": true,
    "EX_fe3hox_LPAREN_e_RPAREN_": true,
    "EX_fe3hox_DASH_un_LPAREN_e_RPAREN_": true,
    "EX_fecrm_LPAREN_e_RPAREN_": true,
    "EX_fecrm_DASH_un_LPAREN_e_RPAREN_": true,
    "EX_feenter_LPAREN_e_RPAREN_": true,
    "EX_feoxam_LPAREN_e_RPAREN_": true,
    "EX_feoxam_DASH_un_LPAREN_e_RPAREN_": true,
    "EX_for_LPAREN_e_RPAREN_": true,
    "EX_fru_LPAREN_e_RPAREN_": true,
    "EX_frulys_LPAREN_e_RPAREN_": true,
    "EX_fruur_LPAREN_e_RPAREN_": true,
    "EX_fuc_DASH_L_LPAREN_e_RPAREN_": true,
    "EX_fum_LPAREN_e_RPAREN_": true,
    "EX_fusa_LPAREN_e_RPAREN_": true,
    "EX_g1p_LPAREN_e_RPAREN_": true,
    "EX_g3pc_LPAREN_e_RPAREN_": true,
    "EX_g3pe_LPAREN_e_RPAREN_": true,
    "EX_g3pg_LPAREN_e_RPAREN_": true,
    "EX_g3pi_LPAREN_e_RPAREN_": true,
    "EX_g3ps_LPAREN_e_RPAREN_": true,
    "EX_g6p_LPAREN_e_RPAREN_": true,
    "EX_gal_LPAREN_e_RPAREN_": true,
    "EX_gal_DASH_bD_LPAREN_e_RPAREN_": true,
    "EX_gal1p_LPAREN_e_RPAREN_": true,
    "EX_galct_DASH_D_LPAREN_e_RPAREN_": true,
    "EX_galctn_DASH_D_LPAREN_e_RPAREN_": true,
    "EX_galctn_DASH_L_LPAREN_e_RPAREN_": true,
    "EX_galt_LPAREN_e_RPAREN_": true,
    "EX_galur_LPAREN_e_RPAREN_": true,
    "EX_gam_LPAREN_e_RPAREN_": true,
    "EX_gam6p_LPAREN_e_RPAREN_": true,
    "EX_gbbtn_LPAREN_e_RPAREN_": true,
    "EX_gdp_LPAREN_e_RPAREN_": true,
    "EX_glc_LPAREN_e_RPAREN_": true,
    "EX_glcn_LPAREN_e_RPAREN_": true,
    "EX_glcr_LPAREN_e_RPAREN_": true,
    "EX_glcur_LPAREN_e_RPAREN_": true,
    "EX_glcur1p_LPAREN_e_RPAREN_": true,
    "EX_gln_DASH_L_LPAREN_e_RPAREN_": true,
    "EX_glu_DASH_L_LPAREN_e_RPAREN_": true,
    "EX_gly_LPAREN_e_RPAREN_": true,
    "EX_glyald_LPAREN_e_RPAREN_": true,
    "EX_glyb_LPAREN_e_RPAREN_": true,
    "EX_glyc_LPAREN_e_RPAREN_": true,
    "EX_glyc_DASH_R_LPAREN_e_RPAREN_": true,
    "EX_glyc2p_LPAREN_e_RPAREN_": true,
    "EX_glyc3p_LPAREN_e_RPAREN_": true,
    "EX_glyclt_LPAREN_e_RPAREN_": true,
    "EX_gmp_LPAREN_e_RPAREN_": true,
    "EX_gsn_LPAREN_e_RPAREN_": true,
    "EX_gthox_LPAREN_e_RPAREN_": true,
    "EX_gthrd_LPAREN_e_RPAREN_": true,
    "EX_gtp_LPAREN_e_RPAREN_": true,
    "EX_gua_LPAREN_e_RPAREN_": true,
    "EX_h_LPAREN_e_RPAREN_": true,
    "EX_h2_LPAREN_e_RPAREN_": true,
    "EX_h2o_LPAREN_e_RPAREN_": false,
    "EX_h2o2_LPAREN_e_RPAREN_": true,
    "EX_h2s_LPAREN_e_RPAREN_": true,
    "EX_hacolipa_LPAREN_e_RPAREN_": true,
    "EX_halipa_LPAREN_e_RPAREN_": true,
    "EX_hdca_LPAREN_e_RPAREN_": true,
    "EX_hdcea_LPAREN_e_RPAREN_": true,
    "EX_hg2_LPAREN_e_RPAREN_": true,
    "EX_his_DASH_L_LPAREN_e_RPAREN_": true,
    "EX_hom_DASH_L_LPAREN_e_RPAREN_": true,
    "EX_hxa_LPAREN_e_RPAREN_": true,
    "EX_hxan_LPAREN_e_RPAREN_": true,
    "EX_idon_DASH_L_LPAREN_e_RPAREN_": true,
    "EX_ile_DASH_L_LPAREN_e_RPAREN_": true,
    "EX_imp_LPAREN_e_RPAREN_": true,
    "EX_indole_LPAREN_e_RPAREN_": true,
    "EX_inost_LPAREN_e_RPAREN_": true,
    "EX_ins_LPAREN_e_RPAREN_": true,
    "EX_isetac_LPAREN_e_RPAREN_": true,
    "EX_k_LPAREN_e_RPAREN_": true,
    "EX_kdo2lipid4_LPAREN_e_RPAREN_": true,
    "EX_lac_DASH_D_LPAREN_e_RPAREN_": true,
    "EX_lac_DASH_L_LPAREN_e_RPAREN_": true,
    "EX_lcts_LPAREN_e_RPAREN_": true,
    "EX_leu_DASH_L_LPAREN_e_RPAREN_": true,
    "EX_lipa_LPAREN_e_RPAREN_": true,
    "EX_lipa_cold_LPAREN_e_RPAREN_": true,
    "EX_lipoate_LPAREN_e_RPAREN_": true,
    "EX_lys_DASH_L_LPAREN_e_RPAREN_": true,
    "EX_lyx_DASH_L_LPAREN_e_RPAREN_": true,
    "EX_mal_DASH_D_LPAREN_e_RPAREN_": true,
    "EX_mal_DASH_L_LPAREN_e_RPAREN_": true,
    "EX_malt_LPAREN_e_RPAREN_": true,
    "EX_malthx_LPAREN_e_RPAREN_": true,
    "EX_maltpt_LPAREN_e_RPAREN_": true,
    "EX_malttr_LPAREN_e_RPAREN_": true,
    "EX_maltttr_LPAREN_e_RPAREN_": true,
    "EX_man_LPAREN_e_RPAREN_": true,
    "EX_man6p_LPAREN_e_RPAREN_": true,
    "EX_manglyc_LPAREN_e_RPAREN_": true,
    "EX_melib_LPAREN_e_RPAREN_": true,
    "EX_meoh_LPAREN_e_RPAREN_": false,
    "EX_met_DASH_D_LPAREN_e_RPAREN_": true,
    "EX_met_DASH_L_LPAREN_e_RPAREN_": true,
    "EX_metsox_DASH_R_DASH_L_LPAREN_e_RPAREN_": true,
    "EX_metsox_DASH_S_DASH_L_LPAREN_e_RPAREN_": true,
    "EX_mg2_LPAREN_e_RPAREN_": true,
    "EX_mincyc_LPAREN_e_RPAREN_": true,
    "EX_minohp_LPAREN_e_RPAREN_": true,
    "EX_mmet_LPAREN_e_RPAREN_": true,
    "EX_mn2_LPAREN_e_RPAREN_": true,
    "EX_mnl_LPAREN_e_RPAREN_": true,
    "EX_mobd_LPAREN_e_RPAREN_": true,
    "EX_mso3_LPAREN_e_RPAREN_": true,
    "EX_n2o_LPAREN_e_RPAREN_": true,
    "EX_na1_LPAREN_e_RPAREN_": true,
    "EX_nac_LPAREN_e_RPAREN_": true,
    "EX_nh4_LPAREN_e_RPAREN_": false,
    "EX_ni2_LPAREN_e_RPAREN_": true,
    "EX_nmn_LPAREN_e_RPAREN_": true,
    "EX_no_LPAREN_e_RPAREN_": true,
    "EX_no2_LPAREN_e_RPAREN_": true,
    "EX_no3_LPAREN_e_RPAREN_": true,
    "EX_novbcn_LPAREN_e_RPAREN_": true,
    "EX_o16a4colipa_LPAREN_e_RPAREN_": true,
    "EX_o2_LPAREN_e_RPAREN_": true,
    "EX_o2s_LPAREN_e_RPAREN_": true,
    "EX_ocdca_LPAREN_e_RPAREN_": true,
    "EX_ocdcea_LPAREN_e_RPAREN_": true,
    "EX_octa_LPAREN_e_RPAREN_": true,
    "EX_orn_LPAREN_e_RPAREN_": true,
    "EX_orot_LPAREN_e_RPAREN_": true,
    "EX_pacald_LPAREN_e_RPAREN_": true,
    "EX_peamn_LPAREN_e_RPAREN_": true,
    "EX_phe_DASH_L_LPAREN_e_RPAREN_": true,
    "EX_pheme_LPAREN_e_RPAREN_": true,
    "EX_pi_LPAREN_e_RPAREN_": true,
    "EX_pnto_DASH_R_LPAREN_e_RPAREN_": true,
    "EX_ppa_LPAREN_e_RPAREN_": true,
    "EX_ppal_LPAREN_e_RPAREN_": true,
    "EX_pppn_LPAREN_e_RPAREN_": true,
    "EX_ppt_LPAREN_e_RPAREN_": true,
    "EX_pro_DASH_L_LPAREN_e_RPAREN_": true,
    "EX_progly_LPAREN_e_RPAREN_": true,
    "EX_psclys_LPAREN_e_RPAREN_": true,
    "EX_pser_DASH_L_LPAREN_e_RPAREN_": true,
    "EX_ptrc_LPAREN_e_RPAREN_": true,
    "EX_pydam_LPAREN_e_RPAREN_": true,
    "EX_pydx_LPAREN_e_RPAREN_": true,
    "EX_pydxn_LPAREN_e_RPAREN_": true,
    "EX_pyr_LPAREN_e_RPAREN_": true,
    "EX_quin_LPAREN_e_RPAREN_": true,
    "EX_r5p_LPAREN_e_RPAREN_": true,
    "EX_rfamp_LPAREN_e_RPAREN_": true,
    "EX_rib_DASH_D_LPAREN_e_RPAREN_": true,
    "EX_rmn_LPAREN_e_RPAREN_": true,
    "EX_sbt_DASH_D_LPAREN_e_RPAREN_": true,
    "EX_sel_LPAREN_e_RPAREN_": true,
    "EX_ser_DASH_D_LPAREN_e_RPAREN_": true,
    "EX_ser_DASH_L_LPAREN_e_RPAREN_": true,
    "EX_skm_LPAREN_e_RPAREN_": true,
    "EX_slnt_LPAREN_e_RPAREN_": true,
    "EX_so2_LPAREN_e_RPAREN_": true,
    "EX_so3_LPAREN_e_RPAREN_": true,
    "EX_so4_LPAREN_e_RPAREN_": true,
    "EX_spmd_LPAREN_e_RPAREN_": true,
    "EX_succ_LPAREN_e_RPAREN_": true,
    "EX_sucr_LPAREN_e_RPAREN_": true,
    "EX_sulfac_LPAREN_e_RPAREN_": true,
    "EX_tartr_DASH_D_LPAREN_e_RPAREN_": true,
    "EX_tartr_DASH_L_LPAREN_e_RPAREN_": true,
    "EX_taur_LPAREN_e_RPAREN_": true,
    "EX_tcynt_LPAREN_e_RPAREN_": true,
    "EX_thm_LPAREN_e_RPAREN_": true,
    "EX_thr_DASH_L_LPAREN_e_RPAREN_": true,
    "EX_thrp_LPAREN_e_RPAREN_": true,
    "EX_thym_LPAREN_e_RPAREN_": true,
    "EX_thymd_LPAREN_e_RPAREN_": true,
    "EX_tma_LPAREN_e_RPAREN_": true,
    "EX_tmao_LPAREN_e_RPAREN_": true,
    "EX_tre_LPAREN_e_RPAREN_": true,
    "EX_trp_DASH_L_LPAREN_e_RPAREN_": true,
    "EX_tsul_LPAREN_e_RPAREN_": true,
    "EX_ttdca_LPAREN_e_RPAREN_": true,
    "EX_ttdcea_LPAREN_e_RPAREN_": true,
    "EX_ttrcyc_LPAREN_e_RPAREN_": true,
    "EX_tungs_LPAREN_e_RPAREN_": true,
    "EX_tym_LPAREN_e_RPAREN_": true,
    "EX_tyr_DASH_L_LPAREN_e_RPAREN_": true,
    "EX_tyrp_LPAREN_e_RPAREN_": true,
    "EX_uacgam_LPAREN_e_RPAREN_": true,
    "EX_udpacgal_LPAREN_e_RPAREN_": true,
    "EX_udpg_LPAREN_e_RPAREN_": true,
    "EX_udpgal_LPAREN_e_RPAREN_": true,
    "EX_udpglcur_LPAREN_e_RPAREN_": true,
    "EX_ump_LPAREN_e_RPAREN_": true,
    "EX_ura_LPAREN_e_RPAREN_": true,
    "EX_urea_LPAREN_e_RPAREN_": true,
    "EX_uri_LPAREN_e_RPAREN_": true,
    "EX_val_DASH_L_LPAREN_e_RPAREN_": true,
    "EX_xan_LPAREN_e_RPAREN_": true,
    "EX_xmp_LPAREN_e_RPAREN_": true,
    "EX_xtsn_LPAREN_e_RPAREN_": true,
    "EX_xyl_DASH_D_LPAREN_e_RPAREN_": true,
    "EX_xylu_DASH_L_LPAREN_e_RPAREN_": true,
    "EX_zn2_LPAREN_e_RPAREN_": true,
    "12DGR120tipp": true,
    "12DGR140tipp": true,
    "12DGR141tipp": true,
    "12DGR160tipp": true,
    "12DGR161tipp": true,
    "12DGR180tipp": true,
    "12DGR181tipp": true,
    "12PPDRtex": true,
    "12PPDRtpp": true,
    "12PPDStex": true,
    "12PPDStpp": true,
    "14GLUCANabcpp": true,
    "14GLUCANtexi": true,
    "23CAMPtex": true,
    "23CCMPtex": true,
    "23CGMPtex": true,
    "23CUMPtex": true,
    "23DAPPAt2pp": true,
    "23DAPPAtex": true,
    "23PDE2pp": true,
    "23PDE4pp": true,
    "23PDE7pp": true,
    "23PDE9pp": true,
    "26DAHtex": true,
    "2AGPA120tipp": true,
    "2AGPA140tipp": true,
    "2AGPA141tipp": true,
    "2AGPA160tipp": true,
    "2AGPA161tipp": true,
    "2AGPA180tipp": true,
    "2AGPA181tipp": true,
    "2AGPE120tipp": true,
    "2AGPE140tipp": true,
    "2AGPE141tipp": true,
    "2AGPE160tipp": true,
    "2AGPE161tipp": true,
    "2AGPE180tipp": true,
    "2AGPE181tipp": true,
    "2AGPEAT120": true,
    "2AGPEAT140": true,
    "2AGPEAT141": true,
    "2AGPEAT160": true,
    "2AGPEAT161": true,
    "2AGPEAT180": true,
    "2AGPEAT181": true,
    "2AGPG120tipp": true,
    "2AGPG140tipp": true,
    "2AGPG141tipp": true,
    "2AGPG160tipp": true,
    "2AGPG161tipp": true,
    "2AGPG180tipp": true,
    "2AGPG181tipp": true,
    "2AGPGAT120": true,
    "2AGPGAT140": true,
    "2AGPGAT141": true,
    "2AGPGAT160": true,
    "2AGPGAT161": true,
    "2AGPGAT180": true,
    "2AGPGAT181": true,
    "2DGULRGx": true,
    "2DGULRGy": true,
    "2DGULRx": true,
    "2DGULRy": true,
    "2MAHMP": true,
    "34dhpactex": true,
    "3AMACHYD": true,
    "3AMPtex": true,
    "3CMPtex": true,
    "3GMPtex": true,
    "3HAD100": true,
    "3HAD120": true,
    "3HAD121": true,
    "3HAD140": true,
    "3HAD141": true,
    "3HAD160": true,
    "3HAD161": true,
    "3HAD180": true,
    "3HAD181": true,
    "3HAD40": true,
    "3HAD60": true,
    "3HAD80": true,
    "3HCINNMH": true,
    "3HPPPNH": true,
    "3HPPtex": true,
    "3HPPtpp": true,
    "3KGK": true,
    "3NTD2pp": true,
    "3NTD4pp": true,
    "3NTD7pp": true,
    "3NTD9pp": true,
    "3OAR100": true,
    "3OAR120": true,
    "3OAR121": true,
    "3OAR140": true,
    "3OAR141": true,
    "3OAR160": true,
    "3OAR161": true,
    "3OAR180": true,
    "3OAR181": true,
    "3OAR40": true,
    "3OAR60": true,
    "3OAR80": true,
    "3OAS100": true,
    "3OAS120": true,
    "3OAS121": true,
    "3OAS140": true,
    "3OAS141": true,
    "3OAS160": true,
    "3OAS161": true,
    "3OAS180": true,
    "3OAS181": true,
    "3OAS60": true,
    "3OAS80": true,
    "3OXCOAT": true,
    "3PEPTabcpp": true,
    "3PEPTtex": true,
    "3UMPtex": true,
    "42A12BOOXpp": true,
    "4HOXPACDtex": true,
    "4HTHRS": true,
    "4PCP": true,
    "4PCPpp": true,
    "4PEPTabcpp": true,
    "4PEPTtex": true,
    "5DGLCNR": true,
    "5DGLCNt2rpp": true,
    "5DGLCNtex": true,
    "5DOAN": true,
    "5MTRtex": true,
    "5MTRtpp": true,
    "A5PISO": true,
    "AACPS1": true,
    "AACPS2": true,
    "AACPS3": true,
    "AACPS4": true,
    "AACPS5": true,
    "AACPS6": true,
    "AACPS7": true,
    "AACPS8": true,
    "AACPS9": true,
    "AACTOOR": true,
    "AADDGT": true,
    "AAMYL": true,
    "AAMYLpp": true,
    "AB6PGH": true,
    "ABTA": true,
    "ABUTD": true,
    "ABUTt2pp": true,
    "ABUTtex": true,
    "ACACCT": true,
    "ACACT1r": false,
    "ACACT2r": false,
    "ACACT3r": false,
    "ACACT4r": false,
    "ACACT5r": false,
    "ACACT6r": false,
    "ACACT7r": false,
    "ACACT8r": false,
    "ACACt2pp": true,
    "ACACtex": true,
    "ACALD": true,
    "ACALDtex": true,
    "ACALDtpp": true,
    "ACANTHAT": true,
    "ACBIPGT": true,
    "ACCOAC": false,
    "ACCOAL": true,
    "ACGAL1PPpp": true,
    "ACGAL1Ptex": true,
    "ACGALtex": true,
    "ACGAM1PPpp": true,
    "ACGAM1Ptex": true,
    "ACGAMK": true,
    "ACGAMT": true,
    "ACGAptspp": true,
    "ACGAtex": true,
    "ACGK": false,
    "ACGS": true,
    "ACHBS": true,
    "ACKr": true,
    "ACLS": true,
    "ACM6PH": true,
    "ACMAMUT": true,
    "ACMANAptspp": true,
    "ACMANAtex": true,
    "ACMUMptspp": true,
    "ACMUMtex": true,
    "ACNAMt2pp": true,
    "ACNAMtex": true,
    "ACNML": true,
    "ACOAD1f": true,
    "ACOAD2f": true,
    "ACOAD3f": true,
    "ACOAD4f": true,
    "ACOAD5f": true,
    "ACOAD6f": true,
    "ACOAD7f": true,
    "ACOAD8f": true,
    "ACOATA": true,
    "ACODA": true,
    "ACOLIPAabctex": true,
    "ACONIs": true,
    "ACONMT": true,
    "ACONTa": false,
    "ACONTb": true,
    "ACOTA": true,
    "ACPPAT120": true,
    "ACPPAT140": true,
    "ACPPAT141": true,
    "ACPPAT160": true,
    "ACPPAT161": true,
    "ACPPAT180": true,
    "ACPPAT181": true,
    "ACPS1": true,
    "ACS": true,
    "ACSERtex": true,
    "ACSERtpp": true,
    "ACt2rpp": true,
    "ACt4pp": true,
    "ACtex": true,
    "ADA": true,
    "ADCL": true,
    "ADCS": true,
    "ADD": true,
    "ADEt2rpp": true,
    "ADEtex": true,
    "ADK1": true,
    "ADK3": true,
    "ADK4": true,
    "ADMDC": true,
    "ADNCYC": true,
    "ADNK1": true,
    "ADNUC": true,
    "ADNt2pp": true,
    "ADNt2rpp": true,
    "ADNtex": true,
    "ADOCBIK": true,
    "ADOCBLS": true,
    "ADOCBLabcpp": true,
    "ADOCBLtonex": true,
    "ADPRDP": true,
    "ADPT": true,
    "ADSK": false,
    "ADSL1r": true,
    "ADSL2r": false,
    "ADSS": false,
    "AGDC": true,
    "AGM3PA": true,
    "AGM3PApp": true,
    "AGM3PH": true,
    "AGM3Pt2pp": true,
    "AGM4PA": true,
    "AGM4PApp": true,
    "AGM4PCP": true,
    "AGM4PCPpp": true,
    "AGM4PH": true,
    "AGM4Pt2pp": true,
    "AGMH": true,
    "AGMHE": true,
    "AGMT": true,
    "AGMt2pp": true,
    "AGMtex": true,
    "AGPAT120": true,
    "AGPAT140": true,
    "AGPAT141": true,
    "AGPAT160": true,
    "AGPAT161": true,
    "AGPAT180": true,
    "AGPAT181": true,
    "AGPR": true,
    "AGt3": true,
    "AHCYSNS": true,
    "AICART": false,
    "AIRC2": false,
    "AIRC3": true,
    "AKGDH": true,
    "AKGt2rpp": true,
    "AKGtex": true,
    "ALAALAD": true,
    "ALAALAabcpp": true,
    "ALAALAr": false,
    "ALAALAtex": true,
    "ALAGLUE": true,
    "ALAR": true,
    "ALATA_D2": true,
    "ALATA_L": true,
    "ALATA_L2": true,
    "ALATRS": true,
    "ALAabcpp": true,
    "ALAt2pp": true,
    "ALAt2rpp": true,
    "ALAt4pp": true,
    "ALAtex": true,
    "ALCD19": true,
    "ALCD2x": true,
    "ALDD19xr": true,
    "ALDD2x": true,
    "ALDD2y": true,
    "ALDD3y": true,
    "ALDD4": true,
    "ALLK": true,
    "ALLPI": true,
    "ALLTAMH": true,
    "ALLTN": true,
    "ALLTNt2rpp": true,
    "ALLTNtex": true,
    "ALLULPE": true,
    "ALLabcpp": true,
    "ALLtex": true,
    "ALPATE160pp": true,
    "ALPATG160pp": true,
    "ALR2": true,
    "ALR4x": true,
    "ALTRH": true,
    "AM3PA": true,
    "AM4PA": true,
    "AM4PCP": true,
    "AMALT1": true,
    "AMALT2": true,
    "AMALT3": true,
    "AMALT4": true,
    "AMANAPEr": true,
    "AMANK": true,
    "AMAOTr": true,
    "AMMQLT8": true,
    "AMPMS2": true,
    "AMPN": true,
    "AMPTASECG": true,
    "AMPTASEPG": true,
    "AMPtex": true,
    "ANHGMtex": true,
    "ANHMK": true,
    "ANPRT": true,
    "ANS": true,
    "AOBUTDs": true,
    "AOXSr2": true,
    "AP4AH": true,
    "AP4AS": true,
    "AP5AH": true,
    "APCS": true,
    "APG3PAT120": true,
    "APG3PAT140": true,
    "APG3PAT141": true,
    "APG3PAT160": false,
    "APG3PAT161": false,
    "APG3PAT180": true,
    "APG3PAT181": false,
    "APH120": true,
    "APH140": true,
    "APH141": true,
    "APH160": true,
    "APH161": true,
    "APH180": true,
    "APH181": true,
    "APPLDHr": true,
    "APRAUR": true,
    "ARAI": true,
    "ARBTNR1": true,
    "ARBTNR2": true,
    "ARBTNR3": true,
    "ARBTNabcpp": true,
    "ARBTNexs": true,
    "ARBTNtex": true,
    "ARBTNtonex": true,
    "ARBTNtpp": true,
    "ARBTptspp": true,
    "ARBTtex": true,
    "ARBabcpp": true,
    "ARBt2rpp": true,
    "ARBt3ipp": true,
    "ARBtex": true,
    "ARGAGMt7pp": true,
    "ARGDC": true,
    "ARGDCpp": true,
    "ARGORNt7pp": true,
    "ARGSL": true,
    "ARGSS": false,
    "ARGTRS": true,
    "ARGabcpp": true,
    "ARGt3pp": true,
    "ARGtex": true,
    "ASAD": true,
    "ASCBPL": true,
    "ASCBptspp": true,
    "ASCBtex": true,
    "ASNN": true,
    "ASNNpp": true,
    "ASNS1": true,
    "ASNS2": false,
    "ASNTRS": true,
    "ASNabcpp": true,
    "ASNt2rpp": true,
    "ASNtex": true,
    "ASO3t8pp": true,
    "ASO3tex": true,
    "ASP1DC": true,
    "ASPCT": false,
    "ASPK": true,
    "ASPO3": true,
    "ASPO4": true,
    "ASPO5": true,
    "ASPO6": true,
    "ASPT": true,
    "ASPTA": true,
    "ASPTRS": true,
    "ASPabcpp": true,
    "ASPt2_2pp": true,
    "ASPt2_3pp": true,
    "ASPt2pp": true,
    "ASPt2rpp": true,
    "ASPtex": true,
    "ASR": true,
    "AST": true,
    "ATHRDHr": true,
    "ATPHs": true,
    "ATPM": true,
    "ATPPRT": true,
    "ATPS4rpp": true,
    "BALAt2pp": true,
    "BALAtex": true,
    "BETALDHx": true,
    "BETALDHy": true,
    "BMOCOS": true,
    "BMOGDS1": false,
    "BMOGDS2": false,
    "BPNT": true,
    "BSORx": true,
    "BSORy": true,
    "BTNt2ipp": true,
    "BTNtex": true,
    "BTS5": false,
    "BUTCT": true,
    "BUTSO3abcpp": true,
    "BUTSO3tex": true,
    "BUTt2rpp": true,
    "BUTtex": true,
    "BWCOGDS1": true,
    "BWCOGDS2": true,
    "BWCOS": true,
    "CA2t3pp": true,
    "CA2tex": true,
    "CADVtpp": true,
    "CAT": true,
    "CAt6pp": false,
    "CBIAT": true,
    "CBItonex": true,
    "CBIuabcpp": true,
    "CBL1abcpp": false,
    "CBL1tonex": false,
    "CBLAT": true,
    "CBMD": true,
    "CBMKr": false,
    "CBPS": true,
    "CCGS": true,
    "CD2abcpp": true,
    "CD2t3pp": true,
    "CD2tex": true,
    "CD2tpp": true,
    "CDAPPA120": true,
    "CDAPPA140": true,
    "CDAPPA141": true,
    "CDAPPA160": true,
    "CDAPPA161": true,
    "CDAPPA180": true,
    "CDAPPA181": true,
    "CDGR": true,
    "CDGS": true,
    "CDPMEK": false,
    "CFAS160E": true,
    "CFAS160G": true,
    "CFAS180E": true,
    "CFAS180G": true,
    "CGLYabcpp": true,
    "CGLYtex": true,
    "CHLabcpp": true,
    "CHLt2pp": true,
    "CHLtex": true,
    "CHOLD": true,
    "CHORM": true,
    "CHORS": true,
    "CHRPL": true,
    "CHTBSptspp": true,
    "CHTBStex": true,
    "CINNDO": true,
    "CITL": true,
    "CITt3pp": true,
    "CITt7pp": true,
    "CITtex": true,
    "CLIPAabctex": true,
    "CLPNH120pp": true,
    "CLPNH140pp": true,
    "CLPNH141pp": true,
    "CLPNH160pp": true,
    "CLPNH161pp": true,
    "CLPNH180pp": true,
    "CLPNH181pp": true,
    "CLPNS120pp": true,
    "CLPNS140pp": true,
    "CLPNS141pp": true,
    "CLPNS160pp": true,
    "CLPNS161pp": true,
    "CLPNS180pp": true,
    "CLPNS181pp": true,
    "CLt3_2pp": false,
    "CLtex": false,
    "CMPN": true,
    "CMPtex": true,
    "CMtex": true,
    "CMtpp": true,
    "CO2tex": true,
    "CO2tpp": true,
    "COBALT2abcpp": true,
    "COBALT2t3pp": true,
    "COBALT2tex": true,
    "COBALT2tpp": true,
    "COLIPAKpp": true,
    "COLIPAPabctex": true,
    "COLIPAabcpp": false,
    "COLIPAabctex": false,
    "CPGNR1": true,
    "CPGNR2": true,
    "CPGNR3": true,
    "CPGNUtex": true,
    "CPGNUtpp": true,
    "CPGNabcpp": true,
    "CPGNexs": true,
    "CPGNtonex": true,
    "CPH4S": true,
    "CPMPS": true,
    "CPPPGO": true,
    "CPPPGO2": true,
    "CRNBTCT": true,
    "CRNCAL2": true,
    "CRNCAR": true,
    "CRNCBCT": true,
    "CRNCDH": true,
    "CRNDCAL2": true,
    "CRNDabcpp": true,
    "CRNDt2rpp": true,
    "CRNDtex": true,
    "CRNabcpp": true,
    "CRNt2rpp": true,
    "CRNt7pp": true,
    "CRNt8pp": true,
    "CRNtex": true,
    "CS": true,
    "CSND": true,
    "CSNt2pp": true,
    "CSNtex": true,
    "CTBTCAL2": true,
    "CTBTabcpp": true,
    "CTBTt2rpp": true,
    "CTECOAI6": true,
    "CTECOAI7": true,
    "CTECOAI8": true,
    "CTPS2": false,
    "CU1Opp": true,
    "CU1abcpp": true,
    "CU2abcpp": true,
    "CU2tex": true,
    "CU2tpp": true,
    "CUt3": true,
    "CUtex": true,
    "CYANST": true,
    "CYANSTpp": true,
    "CYANtex": true,
    "CYNTAH": true,
    "CYNTt2pp": true,
    "CYNTtex": true,
    "CYSDDS": true,
    "CYSDS": true,
    "CYSDabcpp": true,
    "CYSDtex": true,
    "CYSS": true,
    "CYSSADS": true,
    "CYSTL": true,
    "CYSTRS": true,
    "CYSabc2pp": true,
    "CYSabcpp": true,
    "CYStex": true,
    "CYStpp": true,
    "CYTBD2pp": true,
    "CYTBDpp": true,
    "CYTBO3_4pp": true,
    "CYTD": true,
    "CYTDH": true,
    "CYTDK2": true,
    "CYTDt2pp": true,
    "CYTDt2rpp": true,
    "CYTDtex": true,
    "CYTK1": false,
    "CYTK2": true,
    "D_DASH_LACt2pp": true,
    "D_DASH_LACtex": true,
    "DAAD": true,
    "DADA": true,
    "DADK": true,
    "DADNt2pp": true,
    "DADNtex": true,
    "DAGK120": true,
    "DAGK140": true,
    "DAGK141": true,
    "DAGK160": true,
    "DAGK161": true,
    "DAGK180": true,
    "DAGK181": true,
    "DALAt2pp": true,
    "DALAtex": true,
    "DAMPtex": true,
    "DAPAL": true,
    "DAPDC": true,
    "DAPE": true,
    "DAPabcpp": true,
    "DAPtex": true,
    "DASYN120": true,
    "DASYN140": true,
    "DASYN141": true,
    "DASYN160": false,
    "DASYN161": false,
    "DASYN180": true,
    "DASYN181": false,
    "DATPHs": true,
    "DB4PS": true,
    "DBTS": false,
    "DC6PH": true,
    "DCAtex": true,
    "DCMPtex": true,
    "DCTPD": true,
    "DCYTD": true,
    "DCYTt2pp": true,
    "DCYTtex": true,
    "DDCAtexi": true,
    "DDGALK": true,
    "DDGLCNt2rpp": true,
    "DDGLCNtex": true,
    "DDGLK": true,
    "DDPA": true,
    "DDPGALA": true,
    "DGK1": true,
    "DGMPtex": true,
    "DGSNt2pp": true,
    "DGSNtex": true,
    "DHACOAH": true,
    "DHAD1": true,
    "DHAD2": true,
    "DHAPT": true,
    "DHAtex": true,
    "DHAtpp": true,
    "DHBD": true,
    "DHBS": true,
    "DHBSH": true,
    "DHCIND": true,
    "DHCINDO": true,
    "DHDPRy": true,
    "DHDPS": false,
    "DHFR": true,
    "DHFS": false,
    "DHMPTR": true,
    "DHNAOT4": true,
    "DHNCOAS": false,
    "DHNCOAT": true,
    "DHNPA2r": true,
    "DHNPTE": true,
    "DHORD2": true,
    "DHORD5": true,
    "DHORDfum": true,
    "DHORTS": true,
    "DHPPD": true,
    "DHPPDA2": true,
    "DHPS2": true,
    "DHPTDCs2": true,
    "DHPTDNR": true,
    "DHPTDNRN": true,
    "DHPTPE": true,
    "DHQS": true,
    "DHQTi": true,
    "DIMPtex": true,
    "DINSt2pp": true,
    "DINStex": true,
    "DKGLCNR1": true,
    "DKGLCNR2x": true,
    "DKGLCNR2y": true,
    "DMATT": true,
    "DMPPS": true,
    "DMQMT": true,
    "DMSOR1": true,
    "DMSOR1pp": true,
    "DMSOR2": true,
    "DMSOR2pp": true,
    "DMSOtex": true,
    "DMSOtpp": true,
    "DMStex": true,
    "DNMPPA": true,
    "DNTPPA": true,
    "DOGULNR": true,
    "DOPAtex": true,
    "DOXRBCNtex": true,
    "DOXRBCNtpp": true,
    "DPCOAK": false,
    "DPR": true,
    "DRPA": true,
    "DSBAO1": true,
    "DSBAO2": true,
    "DSBCGT": true,
    "DSBDR": true,
    "DSBGGT": true,
    "DSERDHr": true,
    "DSERt2pp": true,
    "DSERtex": true,
    "DTARTD": true,
    "DTMPK": true,
    "DTMPtex": true,
    "DUMPtex": true,
    "DURADx": true,
    "DURIK1": true,
    "DURIPP": true,
    "DURIt2pp": true,
    "DURItex": true,
    "DUTPDP": true,
    "DXPRIi": true,
    "DXPS": true,
    "DXYLK": true,
    "E4PD": false,
    "EAR100x": true,
    "EAR100y": true,
    "EAR120x": true,
    "EAR120y": true,
    "EAR121x": true,
    "EAR121y": true,
    "EAR140x": true,
    "EAR140y": true,
    "EAR141x": true,
    "EAR141y": true,
    "EAR160x": true,
    "EAR160y": true,
    "EAR161x": true,
    "EAR161y": true,
    "EAR180x": true,
    "EAR180y": true,
    "EAR181x": true,
    "EAR181y": true,
    "EAR40x": true,
    "EAR40y": true,
    "EAR60x": true,
    "EAR60y": true,
    "EAR80x": true,
    "EAR80y": true,
    "ECA4COLIPAabctex": true,
    "ECA4OALpp": true,
    "ECAP1pp": true,
    "ECAP2pp": true,
    "ECAP3pp": true,
    "ECAtpp": true,
    "ECOAH1": false,
    "ECOAH2": false,
    "ECOAH3": false,
    "ECOAH4": false,
    "ECOAH5": false,
    "ECOAH6": false,
    "ECOAH7": true,
    "ECOAH8": false,
    "EDA": true,
    "EDD": true,
    "EDTXS1": false,
    "EDTXS2": false,
    "EDTXS3": true,
    "EDTXS4": true,
    "EGMEACPR": true,
    "ENLIPAabctex": true,
    "ENO": false,
    "ENTCS": true,
    "ENTERES": true,
    "ENTERES2": true,
    "EPMEACPR": true,
    "ETHAAL": true,
    "ETHAt2pp": true,
    "ETHAtex": true,
    "ETHSO3abcpp": true,
    "ETHSO3tex": true,
    "ETOHtex": true,
    "ETOHtrpp": true,
    "F6PA": true,
    "F6PP": true,
    "F6Pt6_2pp": true,
    "F6Ptex": true,
    "FA100ACPHi": true,
    "FA120ACPHi": true,
    "FA140ACPHi": true,
    "FA141ACPHi": true,
    "FA160ACPHi": true,
    "FA161ACPHi": true,
    "FA80ACPHi": true,
    "FACOAE100": true,
    "FACOAE120": true,
    "FACOAE140": true,
    "FACOAE141": true,
    "FACOAE160": true,
    "FACOAE161": true,
    "FACOAE180": true,
    "FACOAE181": true,
    "FACOAE60": true,
    "FACOAE80": true,
    "FACOAL100t2pp": true,
    "FACOAL120t2pp": true,
    "FACOAL140t2pp": true,
    "FACOAL141t2pp": true,
    "FACOAL160t2pp": true,
    "FACOAL161t2pp": true,
    "FACOAL180t2pp": true,
    "FACOAL181t2pp": true,
    "FACOAL60t2pp": true,
    "FACOAL80t2pp": true,
    "FADRx": true,
    "FADRx2": true,
    "FALDH2": true,
    "FALDtex": true,
    "FALDtpp": true,
    "FALGTHLs": true,
    "FBA": true,
    "FBA3": true,
    "FBP": true,
    "FCI": true,
    "FCLK": true,
    "FCLPA": true,
    "FCLT": false,
    "FDH4pp": true,
    "FDH5pp": true,
    "FDMO": true,
    "FDMO2": true,
    "FDMO3": true,
    "FDMO4": true,
    "FDMO6": true,
    "FE2abcpp": true,
    "FE2t2pp": true,
    "FE2t3pp": true,
    "FE2tex": true,
    "FE2tpp": true,
    "FE3DCITabcpp": true,
    "FE3DCITtonex": true,
    "FE3DHBZR": true,
    "FE3DHBZSabcpp": true,
    "FE3DHBZStonex": true,
    "FE3HOXR1": true,
    "FE3HOXR2": true,
    "FE3HOXR3": true,
    "FE3HOXUtex": true,
    "FE3HOXUtpp": true,
    "FE3HOXabcpp": true,
    "FE3HOXexs": true,
    "FE3HOXtonex": true,
    "FE3Ri": true,
    "FE3abcpp": true,
    "FE3tex": false,
    "FECRMR1": true,
    "FECRMR2": true,
    "FECRMR3": true,
    "FECRMUtex": true,
    "FECRMUtpp": true,
    "FECRMabcpp": true,
    "FECRMexs": true,
    "FECRMtonex": true,
    "FEENTERR1": true,
    "FEENTERR2": true,
    "FEENTERR3": true,
    "FEENTERabcpp": true,
    "FEENTERexs": true,
    "FEENTERtex": true,
    "FEENTERtonex": true,
    "FEENTERtpp": true,
    "FEOXAMR1": true,
    "FEOXAMR2": true,
    "FEOXAMR3": true,
    "FEOXAMUtex": true,
    "FEOXAMUtpp": true,
    "FEOXAMabcpp": true,
    "FEOXAMexs": true,
    "FEOXAMtonex": true,
    "FEROpp": true,
    "FESD1s": true,
    "FESD2s": true,
    "FESR": false,
    "FFSD": true,
    "FHL": true,
    "FLDR2": true,
    "FLVR": true,
    "FLVRx": true,
    "FMETTRS": true,
    "FMNAT": true,
    "FMNRx": true,
    "FMNRx2": true,
    "FOMETRi": true,
    "FORCT": true,
    "FORt2pp": true,
    "FORtex": true,
    "FORtppi": true,
    "FRD2": true,
    "FRD3": true,
    "FRUK": true,
    "FRULYSDG": true,
    "FRULYSE": true,
    "FRULYSK": true,
    "FRULYSt2pp": true,
    "FRULYStex": true,
    "FRUURt2rpp": true,
    "FRUURtex": true,
    "FRUpts2pp": true,
    "FRUptspp": true,
    "FRUtex": true,
    "FTHFD": true,
    "FTHFLi": true,
    "FUCtex": true,
    "FUCtpp": true,
    "FUM": true,
    "FUMt2_2pp": true,
    "FUMt2_3pp": true,
    "FUMtex": true,
    "FUSAtex": true,
    "FUSAtpp": true,
    "G1PACT": false,
    "G1PPpp": true,
    "G1PTT": true,
    "G1Ptex": true,
    "G1SAT": true,
    "G2PP": true,
    "G2PPpp": true,
    "G3PAT120": true,
    "G3PAT140": true,
    "G3PAT141": true,
    "G3PAT160": true,
    "G3PAT161": true,
    "G3PAT180": true,
    "G3PAT181": true,
    "G3PCabcpp": true,
    "G3PCtex": true,
    "G3PD2": true,
    "G3PD5": true,
    "G3PD6": true,
    "G3PD7": true,
    "G3PEabcpp": true,
    "G3PEtex": true,
    "G3PGabcpp": true,
    "G3PGtex": true,
    "G3PIabcpp": true,
    "G3PItex": true,
    "G3PSabcpp": true,
    "G3PStex": true,
    "G3PT": true,
    "G5SADs": false,
    "G5SD": true,
    "G6PDA": true,
    "G6PDH2r": false,
    "G6PP": true,
    "G6Pt6_2pp": true,
    "G6Ptex": true,
    "GAL1PPpp": true,
    "GAL1Ptex": true,
    "GALBDtex": true,
    "GALCTD": true,
    "GALCTLO": true,
    "GALCTND": true,
    "GALCTNLt2pp": true,
    "GALCTNLtex": true,
    "GALCTNt2pp": true,
    "GALCTNtex": true,
    "GALCTt2rpp": true,
    "GALCTtex": true,
    "GALKr": true,
    "GALM2pp": true,
    "GALS3": true,
    "GALT1": false,
    "GALTptspp": true,
    "GALTtex": true,
    "GALURt2rpp": true,
    "GALURtex": true,
    "GALUi": true,
    "GALabcpp": true,
    "GALt2pp": true,
    "GALtex": true,
    "GAM6Pt6_2pp": true,
    "GAMAN6Ptex": true,
    "GAMptspp": true,
    "GAMtex": true,
    "GAPD": false,
    "GARFT": false,
    "GART": true,
    "GBBTNtex": true,
    "GCALDD": false,
    "GDMANE": true,
    "GDPDPK": true,
    "GDPMNH": true,
    "GDPMNP": true,
    "GDPTPDP": true,
    "GDPtex": true,
    "GF6PTA": true,
    "GGGABADr": true,
    "GGGABAH": true,
    "GGPTRCO": true,
    "GGPTRCS": true,
    "GHBDHx": true,
    "GHMT2r": true,
    "GK1": true,
    "GLBRAN2": true,
    "GLCATr": true,
    "GLCDpp": true,
    "GLCNt2rpp": true,
    "GLCNtex": true,
    "GLCP": true,
    "GLCP2": true,
    "GLCRAL": true,
    "GLCRD": true,
    "GLCRt2rpp": true,
    "GLCRtex": true,
    "GLCS1": true,
    "GLCTR1": false,
    "GLCTR2": false,
    "GLCTR3": false,
    "GLCUR1Ptex": true,
    "GLCURt2rpp": true,
    "GLCURtex": true,
    "GLCabcpp": true,
    "GLCptspp": true,
    "GLCt2pp": true,
    "GLCtex": true,
    "GLCtexi": true,
    "GLDBRAN2": true,
    "GLGC": true,
    "GLNS": false,
    "GLNTRS": true,
    "GLNabcpp": true,
    "GLNtex": true,
    "GLTPD": true,
    "GLU5K": true,
    "GLUABUTt7pp": true,
    "GLUCYS": false,
    "GLUDC": true,
    "GLUDy": true,
    "GLUN": true,
    "GLUNpp": true,
    "GLUPRT": true,
    "GLUR": true,
    "GLUSy": true,
    "GLUTRR": true,
    "GLUTRS": false,
    "GLUabcpp": true,
    "GLUt2rpp": true,
    "GLUt4pp": true,
    "GLUtex": true,
    "GLXCL": true,
    "GLYALDtex": true,
    "GLYALDtpp": true,
    "GLYAT": true,
    "GLYBabcpp": true,
    "GLYBt2pp": true,
    "GLYBtex": true,
    "GLYC2Pabcpp": true,
    "GLYC2Ptex": true,
    "GLYC3Pabcpp": true,
    "GLYC3Pt6pp": true,
    "GLYC3Ptex": true,
    "GLYCAt2rpp": true,
    "GLYCAtex": true,
    "GLYCDx": true,
    "GLYCK": true,
    "GLYCK2": true,
    "GLYCL": true,
    "GLYCLTDx": true,
    "GLYCLTDy": true,
    "GLYCLTt2rpp": true,
    "GLYCLTt4pp": true,
    "GLYCLTtex": true,
    "GLYCTO2": true,
    "GLYCTO3": true,
    "GLYCTO4": true,
    "GLYCtex": true,
    "GLYCtpp": false,
    "GLYK": false,
    "GLYOX": true,
    "GLYOX3": true,
    "GLYTRS": true,
    "GLYt2pp": true,
    "GLYt2rpp": true,
    "GLYt4pp": true,
    "GLYtex": true,
    "GMAND": true,
    "GMHEPAT": true,
    "GMHEPK": false,
    "GMHEPPA": true,
    "GMPR": true,
    "GMPS2": false,
    "GMPtex": true,
    "GND": true,
    "GNK": true,
    "GOFUCR": true,
    "GP4GH": true,
    "GPDDA1": true,
    "GPDDA1pp": true,
    "GPDDA2": true,
    "GPDDA2pp": true,
    "GPDDA3": true,
    "GPDDA3pp": true,
    "GPDDA4": true,
    "GPDDA4pp": true,
    "GPDDA5": true,
    "GPDDA5pp": true,
    "GRTT": true,
    "GRXR": true,
    "GSNK": true,
    "GSNt2pp": true,
    "GSNtex": true,
    "GSPMDA": true,
    "GSPMDS": true,
    "GTHOXtex": true,
    "GTHOr": true,
    "GTHPi": true,
    "GTHRDHpp": true,
    "GTHRDabc2pp": true,
    "GTHRDabcpp": true,
    "GTHRDtex": true,
    "GTHS": false,
    "GTPCI": true,
    "GTPCII2": true,
    "GTPDPDP": true,
    "GTPDPK": true,
    "GTPHs": true,
    "GTPtex": true,
    "GUACYC": true,
    "GUAD": true,
    "GUAPRT": true,
    "GUAt2pp": true,
    "GUAtex": true,
    "GUAtpp": true,
    "GUI1": true,
    "GUI2": true,
    "GUR1PPpp": true,
    "H2O2tex": true,
    "H2Otex": true,
    "H2Otpp": true,
    "H2SO": true,
    "H2St1pp": true,
    "H2Stex": true,
    "H2tex": true,
    "H2tpp": true,
    "HACD1": true,
    "HACD2": true,
    "HACD3": true,
    "HACD4": true,
    "HACD5": true,
    "HACD6": true,
    "HACD7": true,
    "HACD8": true,
    "HADPCOADH3": true,
    "HBZOPT": true,
    "HCINNMt2rpp": true,
    "HCINNMtex": true,
    "HCO3E": false,
    "HCYSMT": true,
    "HCYSMT2": true,
    "HDCAtexi": true,
    "HDCEAtexi": true,
    "HEMEOS": true,
    "HEPK1": false,
    "HEPK2": false,
    "HEPT1": true,
    "HEPT2": false,
    "HEPT3": false,
    "HEPT4": false,
    "HETZK": true,
    "HEX1": true,
    "HEX4": true,
    "HEX7": true,
    "HEXt2rpp": true,
    "HG2abcpp": true,
    "HG2t3pp": true,
    "HG2tex": true,
    "HISTD": false,
    "HISTP": true,
    "HISTRS": true,
    "HISabcpp": true,
    "HISt2rpp": true,
    "HIStex": true,
    "HKNDDH": true,
    "HKNTDH": true,
    "HMBS": true,
    "HMPK1": true,
    "HOMt2pp": true,
    "HOMtex": true,
    "HOPNTAL": true,
    "HPPK2": false,
    "HPPPNDO": true,
    "HPPPNt2rpp": true,
    "HPPPNtex": true,
    "HPYRI": true,
    "HPYRRx": true,
    "HPYRRy": true,
    "HSDy": true,
    "HSK": false,
    "HSST": true,
    "HSTPT": true,
    "HXAND": true,
    "HXAtex": true,
    "HXCT": true,
    "HXPRT": true,
    "HYD1pp": true,
    "HYD2pp": true,
    "HYD3pp": true,
    "HYPOE": true,
    "HYXNtex": true,
    "HYXNtpp": true,
    "Htex": false,
    "I2FE2SR": true,
    "I2FE2SS": false,
    "I2FE2SS2": false,
    "I2FE2ST": true,
    "I4FE4SR": true,
    "I4FE4ST": true,
    "ICDHyr": true,
    "ICHORS": true,
    "ICHORSi": true,
    "ICHORT": true,
    "ICL": true,
    "ICYSDS": true,
    "IDOND": true,
    "IDOND2": true,
    "IDONt2rpp": true,
    "IDONtex": true,
    "IG3PS": true,
    "IGPDH": true,
    "IGPS": true,
    "ILETA": true,
    "ILETRS": true,
    "ILEabcpp": true,
    "ILEt2rpp": true,
    "ILEtex": true,
    "IMPC": false,
    "IMPD": false,
    "IMPtex": true,
    "INDOLEt2pp": true,
    "INDOLEt2rpp": true,
    "INDOLEtex": true,
    "INOSTt4pp": true,
    "INSH": true,
    "INSK": true,
    "INSTtex": true,
    "INSt2pp": true,
    "INSt2rpp": true,
    "INStex": true,
    "IPDDI": true,
    "IPDPS": true,
    "IPMD": false,
    "IPPMIa": true,
    "IPPMIb": false,
    "IPPS": true,
    "ISETACabcpp": true,
    "ISETACtex": true,
    "K2L4Aabcpp": true,
    "K2L4Aabctex": true,
    "KARA1": true,
    "KARA2": true,
    "KAS14": true,
    "KAS15": true,
    "KDOCT2": true,
    "KDOPP": true,
    "KDOPS": true,
    "KG6PDC": true,
    "Kabcpp": true,
    "Kt2pp": true,
    "Kt3pp": true,
    "Ktex": true,
    "L_DASH_LACD2": true,
    "L_DASH_LACD3": true,
    "L_DASH_LACt2rpp": true,
    "L_DASH_LACtex": true,
    "LA4NTpp": true,
    "LACZ": true,
    "LACZpp": true,
    "LADGMDH": true,
    "LALADGLUtex": true,
    "LALADGLUtpp": true,
    "LALALGLUtex": true,
    "LALALGLUtpp": true,
    "LALDO2x": true,
    "LALDO3": true,
    "LALGP": true,
    "LCADi": true,
    "LCARR": true,
    "LCARS": true,
    "LCTSt3ipp": true,
    "LCTStex": true,
    "LCTStpp": true,
    "LDH_D": true,
    "LDH_D2": true,
    "LEUTAi": true,
    "LEUTRS": true,
    "LEUabcpp": true,
    "LEUt2rpp": true,
    "LEUtex": true,
    "LGTHL": true,
    "LIPACabcpp": true,
    "LIPAHT2ex": true,
    "LIPAHTex": true,
    "LIPAMPL": true,
    "LIPATPT": true,
    "LIPAabcpp": true,
    "LIPAabctex": true,
    "LIPOCT": true,
    "LIPOS": true,
    "LIPOt2pp": true,
    "LIPOtex": true,
    "LPADSS": false,
    "LPLIPAL1A120pp": true,
    "LPLIPAL1A140pp": true,
    "LPLIPAL1A141pp": true,
    "LPLIPAL1A160pp": true,
    "LPLIPAL1A161pp": true,
    "LPLIPAL1A180pp": true,
    "LPLIPAL1A181pp": true,
    "LPLIPAL1E120pp": true,
    "LPLIPAL1E140pp": true,
    "LPLIPAL1E141pp": true,
    "LPLIPAL1E160pp": true,
    "LPLIPAL1E161pp": true,
    "LPLIPAL1E180pp": true,
    "LPLIPAL1E181pp": true,
    "LPLIPAL1G120pp": true,
    "LPLIPAL1G140pp": true,
    "LPLIPAL1G141pp": true,
    "LPLIPAL1G160pp": true,
    "LPLIPAL1G161pp": true,
    "LPLIPAL1G180pp": true,
    "LPLIPAL1G181pp": true,
    "LPLIPAL2A120": true,
    "LPLIPAL2A140": true,
    "LPLIPAL2A141": true,
    "LPLIPAL2A160": true,
    "LPLIPAL2A161": true,
    "LPLIPAL2A180": true,
    "LPLIPAL2A181": true,
    "LPLIPAL2ATE120": true,
    "LPLIPAL2ATE140": true,
    "LPLIPAL2ATE141": true,
    "LPLIPAL2ATE160": true,
    "LPLIPAL2ATE161": true,
    "LPLIPAL2ATE180": true,
    "LPLIPAL2ATE181": true,
    "LPLIPAL2ATG120": true,
    "LPLIPAL2ATG140": true,
    "LPLIPAL2ATG141": true,
    "LPLIPAL2ATG160": true,
    "LPLIPAL2ATG161": true,
    "LPLIPAL2ATG180": true,
    "LPLIPAL2ATG181": true,
    "LPLIPAL2E120": true,
    "LPLIPAL2E140": true,
    "LPLIPAL2E141": true,
    "LPLIPAL2E160": true,
    "LPLIPAL2E161": true,
    "LPLIPAL2E180": true,
    "LPLIPAL2E181": true,
    "LPLIPAL2G120": true,
    "LPLIPAL2G140": true,
    "LPLIPAL2G141": true,
    "LPLIPAL2G160": true,
    "LPLIPAL2G161": true,
    "LPLIPAL2G180": true,
    "LPLIPAL2G181": true,
    "LSERDHr": true,
    "LYSDC": true,
    "LYSTRS": true,
    "LYSabcpp": true,
    "LYSt2pp": true,
    "LYSt3pp": true,
    "LYStex": true,
    "LYXI": true,
    "LYXt2pp": true,
    "LYXtex": true,
    "M1PD": true,
    "MACPD": true,
    "MALCOAMT": true,
    "MALDDH": true,
    "MALDt2_2pp": true,
    "MALDtex": true,
    "MALS": true,
    "MALTATr": true,
    "MALTHXabcpp": true,
    "MALTHXtexi": true,
    "MALTPTabcpp": true,
    "MALTPTtexi": true,
    "MALTTRabcpp": true,
    "MALTTRtexi": true,
    "MALTTTRabcpp": true,
    "MALTTTRtexi": true,
    "MALTabcpp": true,
    "MALTptspp": true,
    "MALTtexi": true,
    "MALt2_2pp": true,
    "MALt2_3pp": true,
    "MALt3pp": true,
    "MALtex": true,
    "MAN1PT2": true,
    "MAN6PI": true,
    "MAN6Pt6_2pp": true,
    "MAN6Ptex": true,
    "MANAO": true,
    "MANGLYCptspp": true,
    "MANGLYCtex": true,
    "MANPGH": true,
    "MANptspp": true,
    "MANtex": true,
    "MCITD": true,
    "MCITL2": true,
    "MCITS": true,
    "MCOATA": false,
    "MCPST": true,
    "MCTP1App": true,
    "MCTP1Bpp": true,
    "MCTP2App": true,
    "MDDCP1pp": true,
    "MDDCP2pp": true,
    "MDDCP3pp": true,
    "MDDCP4pp": true,
    "MDDCP5pp": true,
    "MDDEP1pp": true,
    "MDDEP2pp": true,
    "MDDEP3pp": true,
    "MDDEP4pp": true,
    "MDH": false,
    "MDH2": true,
    "MDH3": true,
    "ME1": true,
    "ME2": true,
    "MECDPDH5": true,
    "MECDPS": true,
    "MELIBt2pp": true,
    "MELIBt3ipp": true,
    "MELIBtex": true,
    "MEOHtex": true,
    "MEOHtrpp": true,
    "MEPCT": true,
    "METAT": true,
    "METDabcpp": true,
    "METDtex": true,
    "METOX1s": true,
    "METOX2s": true,
    "METS": true,
    "METSOX1abcpp": true,
    "METSOX1tex": true,
    "METSOX2abcpp": true,
    "METSOX2tex": true,
    "METSOXR1": true,
    "METSOXR2": true,
    "METTRS": true,
    "METabcpp": true,
    "METtex": true,
    "MG2t3_2pp": true,
    "MG2tex": true,
    "MG2tpp": true,
    "MG2uabcpp": true,
    "MGSA": true,
    "MI1PP": true,
    "MICITDr": true,
    "MINCYCtex": true,
    "MINCYCtpp": true,
    "MINOHPtexi": true,
    "MLDCP1App": false,
    "MLDCP1Bpp": true,
    "MLDCP2App": true,
    "MLDCP2Bpp": true,
    "MLDCP3App": false,
    "MLDEP1pp": false,
    "MLDEP2pp": true,
    "MLTG1": true,
    "MLTG2": true,
    "MLTG3": true,
    "MLTG4": true,
    "MLTG5": true,
    "MLTGY1pp": true,
    "MLTGY2pp": true,
    "MLTGY3pp": true,
    "MLTGY4pp": true,
    "MLTP1": true,
    "MLTP2": true,
    "MLTP3": true,
    "MMCD": true,
    "MMETt2pp": true,
    "MMETtex": true,
    "MMM": true,
    "MN2t3pp": true,
    "MN2tpp": true,
    "MN6PP": true,
    "MNLptspp": true,
    "MNLtex": true,
    "MNNH": true,
    "MNt2pp": true,
    "MNtex": true,
    "MOADSUx": true,
    "MOAT": true,
    "MOAT2": true,
    "MOAT3C": true,
    "MOBDabcpp": false,
    "MOBDtex": false,
    "MOCDS": false,
    "MOCOS": true,
    "MOGDS": false,
    "MOHMT": true,
    "MOX": true,
    "MPTAT": true,
    "MPTG": true,
    "MPTG2": false,
    "MPTS": true,
    "MPTSS": false,
    "MSAR": true,
    "MSO3abcpp": true,
    "MSO3tex": true,
    "MTAN": true,
    "MTHFC": false,
    "MTHFD": false,
    "MTHFR2": true,
    "MTHTHFSs": false,
    "MTRPOX": true,
    "N2Otex": true,
    "N2Otpp": true,
    "NACODA": true,
    "NACtex": true,
    "NACtpp": true,
    "NADDP": true,
    "NADH10": true,
    "NADH16pp": true,
    "NADH17pp": true,
    "NADH18pp": true,
    "NADH5": true,
    "NADH9": true,
    "NADK": false,
    "NADN": true,
    "NADPHQR2": true,
    "NADPHQR3": true,
    "NADPHQR4": true,
    "NADPPPS": true,
    "NADS1": false,
    "NADTRHD": true,
    "NAMNPP": true,
    "NAt3_1p5pp": true,
    "NAt3_2pp": true,
    "NAt3pp": true,
    "NAtex": true,
    "NDPK1": true,
    "NDPK2": true,
    "NDPK3": true,
    "NDPK4": true,
    "NDPK5": true,
    "NDPK6": true,
    "NDPK7": true,
    "NDPK8": true,
    "NH4tex": true,
    "NH4tpp": true,
    "NHFRBO": true,
    "NI2abcpp": true,
    "NI2t3pp": true,
    "NI2tex": true,
    "NI2tpp": true,
    "NI2uabcpp": true,
    "NMNAT": true,
    "NMNDA": true,
    "NMNN": true,
    "NMNPtpp": true,
    "NMNt7pp": true,
    "NMNtex": true,
    "NNAM": true,
    "NNATr": true,
    "NNDMBRT": true,
    "NNDPR": true,
    "NO2t2rpp": true,
    "NO2tex": true,
    "NO3R1bpp": true,
    "NO3R1pp": true,
    "NO3R2bpp": true,
    "NO3R2pp": true,
    "NO3t7pp": true,
    "NO3tex": true,
    "NODOx": true,
    "NODOy": true,
    "NOVBCNtex": true,
    "NOVBCNtpp": true,
    "NOtex": true,
    "NOtpp": true,
    "NTD1": true,
    "NTD10": true,
    "NTD10pp": true,
    "NTD11": true,
    "NTD11pp": true,
    "NTD12": true,
    "NTD12pp": true,
    "NTD1pp": true,
    "NTD2": true,
    "NTD2pp": true,
    "NTD3": true,
    "NTD3pp": true,
    "NTD4": true,
    "NTD4pp": true,
    "NTD5": true,
    "NTD5pp": true,
    "NTD6": true,
    "NTD6pp": true,
    "NTD7": true,
    "NTD7pp": true,
    "NTD8": true,
    "NTD8pp": true,
    "NTD9": true,
    "NTD9pp": true,
    "NTP1": true,
    "NTP10": true,
    "NTP11": true,
    "NTP12": true,
    "NTP3": true,
    "NTP3pp": true,
    "NTP5": true,
    "NTPP1": true,
    "NTPP10": true,
    "NTPP11": true,
    "NTPP2": true,
    "NTPP3": true,
    "NTPP4": true,
    "NTPP5": true,
    "NTPP6": true,
    "NTPP7": true,
    "NTPP8": true,
    "NTPP9": true,
    "NTPTP1": true,
    "NTPTP2": true,
    "NTRIR2x": true,
    "NTRIR3pp": true,
    "NTRIR4pp": true,
    "O16A4COLIPAabctex": true,
    "O16A4Lpp": true,
    "O16AP1pp": true,
    "O16AP2pp": true,
    "O16AP3pp": true,
    "O16AT": true,
    "O16AUNDtpp": true,
    "O16GALFT": true,
    "O16GLCT1": true,
    "O16GLCT2": true,
    "O2Stex": true,
    "O2tex": true,
    "O2tpp": true,
    "OAADC": true,
    "OBTFL": true,
    "OCBT": true,
    "OCDCAtexi": true,
    "OCDCEAtexi": true,
    "OCTAtex": true,
    "OCTDPS": true,
    "OCTNLL": true,
    "OGMEACPD": true,
    "OGMEACPR": true,
    "OGMEACPS": true,
    "OHPBAT": true,
    "OHPHM": false,
    "OMBZLM": true,
    "OMCDC": true,
    "OMMBLHX": false,
    "OMMBLHX3": true,
    "OMPDC": true,
    "OMPHHX": true,
    "OMPHHX3": true,
    "OP4ENH": true,
    "OPHBDC": true,
    "OPHHX": true,
    "OPHHX3": true,
    "OPMEACPD": true,
    "OPMEACPR": true,
    "OPMEACPS": true,
    "ORNDC": true,
    "ORNabcpp": true,
    "ORNtex": true,
    "OROTt2_2pp": true,
    "OROTtex": true,
    "ORPT": true,
    "OXAMTC": true,
    "OXCDC": true,
    "OXCOAHDH": true,
    "OXDHCOAT": true,
    "P5CD": true,
    "P5CR": true,
    "PA120abcpp": true,
    "PA140abcpp": true,
    "PA141abcpp": true,
    "PA160abcpp": true,
    "PA161abcpp": true,
    "PA180abcpp": true,
    "PA181abcpp": true,
    "PACALDt2rpp": true,
    "PACALDtex": true,
    "PACCOAE": true,
    "PACCOAL": true,
    "PANTS": true,
    "PAPA120": true,
    "PAPA120pp": true,
    "PAPA140": true,
    "PAPA140pp": true,
    "PAPA141": true,
    "PAPA141pp": true,
    "PAPA160": true,
    "PAPA160pp": true,
    "PAPA161": true,
    "PAPA161pp": true,
    "PAPA180": true,
    "PAPA180pp": true,
    "PAPA181": true,
    "PAPA181pp": true,
    "PAPPT3": false,
    "PAPSR": true,
    "PAPSR2": true,
    "PDE1": true,
    "PDE4": true,
    "PDH": true,
    "PDX5PO2": true,
    "PDX5POi": true,
    "PDX5PS": true,
    "PDXPP": true,
    "PE120abcpp": true,
    "PE140abcpp": true,
    "PE141abcpp": true,
    "PE160abcpp": true,
    "PE161abcpp": true,
    "PE180abcpp": true,
    "PE181abcpp": true,
    "PEAMNOpp": true,
    "PEAMNtex": true,
    "PERD": false,
    "PETNT161pp": true,
    "PETNT181pp": true,
    "PFK": true,
    "PFK_2": true,
    "PFK_3": true,
    "PFL": true,
    "PG120abcpp": true,
    "PG140abcpp": true,
    "PG141abcpp": true,
    "PG160abcpp": false,
    "PG161abcpp": false,
    "PG180abcpp": true,
    "PG181abcpp": false,
    "PGAMT": false,
    "PGCD": false,
    "PGI": true,
    "PGK": true,
    "PGL": false,
    "PGLYCP": true,
    "PGM": false,
    "PGMT": true,
    "PGP120abcpp": true,
    "PGP140abcpp": true,
    "PGP141abcpp": true,
    "PGP160abcpp": true,
    "PGP161abcpp": true,
    "PGP180abcpp": true,
    "PGP181abcpp": true,
    "PGPP120": true,
    "PGPP120pp": true,
    "PGPP140": true,
    "PGPP140pp": true,
    "PGPP141": true,
    "PGPP141pp": true,
    "PGPP160": true,
    "PGPP160pp": true,
    "PGPP161": true,
    "PGPP161pp": true,
    "PGPP180": true,
    "PGPP180pp": true,
    "PGPP181": true,
    "PGPP181pp": true,
    "PGSA120": true,
    "PGSA140": true,
    "PGSA141": true,
    "PGSA160": false,
    "PGSA161": false,
    "PGSA180": true,
    "PGSA181": false,
    "PHEMEabcpp": true,
    "PHEMEtiex": true,
    "PHETA1": true,
    "PHETRS": true,
    "PHEt2rpp": true,
    "PHEtex": true,
    "PHYTSpp": true,
    "PIt2rpp": false,
    "PItex": false,
    "PIuabcpp": true,
    "PLIPA1A120pp": true,
    "PLIPA1A140pp": true,
    "PLIPA1A141pp": true,
    "PLIPA1A160pp": true,
    "PLIPA1A161pp": true,
    "PLIPA1A180pp": true,
    "PLIPA1A181pp": true,
    "PLIPA1E120pp": true,
    "PLIPA1E140pp": true,
    "PLIPA1E141pp": true,
    "PLIPA1E160pp": true,
    "PLIPA1E161pp": true,
    "PLIPA1E180pp": true,
    "PLIPA1E181pp": true,
    "PLIPA1G120pp": true,
    "PLIPA1G140pp": true,
    "PLIPA1G141pp": true,
    "PLIPA1G160pp": true,
    "PLIPA1G161pp": true,
    "PLIPA1G180pp": true,
    "PLIPA1G181pp": true,
    "PLIPA2A120pp": true,
    "PLIPA2A140pp": true,
    "PLIPA2A141pp": true,
    "PLIPA2A160pp": true,
    "PLIPA2A161pp": true,
    "PLIPA2A180pp": true,
    "PLIPA2A181pp": true,
    "PLIPA2E120pp": true,
    "PLIPA2E140pp": true,
    "PLIPA2E141pp": true,
    "PLIPA2E160pp": true,
    "PLIPA2E161pp": true,
    "PLIPA2E180pp": true,
    "PLIPA2E181pp": true,
    "PLIPA2G120pp": true,
    "PLIPA2G140pp": true,
    "PLIPA2G141pp": true,
    "PLIPA2G160pp": true,
    "PLIPA2G161pp": true,
    "PLIPA2G180pp": true,
    "PLIPA2G181pp": true,
    "PMANM": true,
    "PMDPHT": true,
    "PMEACPE": false,
    "PMPK": true,
    "PNTK": false,
    "PNTOt4pp": true,
    "PNTOtex": true,
    "POAACR": true,
    "POR5": true,
    "POX": true,
    "PPA": true,
    "PPA2": true,
    "PPAKr": true,
    "PPALtex": true,
    "PPALtpp": true,
    "PPAt4pp": true,
    "PPAtex": true,
    "PPBNGS": true,
    "PPC": true,
    "PPCDC": true,
    "PPCK": true,
    "PPCSCT": true,
    "PPGPPDP": true,
    "PPK2r": true,
    "PPKr": false,
    "PPM": true,
    "PPM2": true,
    "PPNCL2": true,
    "PPND": true,
    "PPNDH": true,
    "PPPGO": true,
    "PPPGO3": false,
    "PPPNDO": true,
    "PPPNt2rpp": true,
    "PPPNtex": true,
    "PPS": true,
    "PPTHpp": true,
    "PPTtex": true,
    "PRAGSr": false,
    "PRAIS": false,
    "PRAIi": true,
    "PRAMPC": false,
    "PRASCSi": false,
    "PRATPP": true,
    "PRFGS": true,
    "PRMICI": true,
    "PROD2": true,
    "PROGLYabcpp": true,
    "PROGLYtex": true,
    "PROTRS": true,
    "PROabcpp": true,
    "PROt2rpp": true,
    "PROt4pp": true,
    "PROtex": true,
    "PRPPS": true,
    "PSCLYSt2pp": true,
    "PSCLYStex": true,
    "PSCVT": true,
    "PSD120": true,
    "PSD140": true,
    "PSD141": true,
    "PSD160": true,
    "PSD161": true,
    "PSD180": true,
    "PSD181": true,
    "PSERT": true,
    "PSERtex": true,
    "PSP_L": true,
    "PSP_Lpp": true,
    "PSSA120": true,
    "PSSA140": true,
    "PSSA141": true,
    "PSSA160": true,
    "PSSA161": true,
    "PSSA180": true,
    "PSSA181": true,
    "PTA2": true,
    "PTAr": true,
    "PTHRpp": true,
    "PTPATi": true,
    "PTRCORNt7pp": true,
    "PTRCTA": true,
    "PTRCabcpp": true,
    "PTRCt2pp": true,
    "PTRCtex": true,
    "PUNP1": true,
    "PUNP2": true,
    "PUNP3": true,
    "PUNP4": true,
    "PUNP5": true,
    "PUNP6": true,
    "PUNP7": true,
    "PYAM5PO": true,
    "PYDAMK": true,
    "PYDAMtex": true,
    "PYDAMtpp": true,
    "PYDXK": true,
    "PYDXNK": true,
    "PYDXNtex": true,
    "PYDXNtpp": true,
    "PYDXPP": true,
    "PYDXtex": true,
    "PYDXtpp": true,
    "PYK": true,
    "PYNP2r": true,
    "PYROX": true,
    "PYRt2rpp": true,
    "PYRtex": true,
    "QMO2": true,
    "QMO3": true,
    "QUIN2tex": true,
    "QUIN2tpp": true,
    "QUINDH": true,
    "QULNS": true,
    "R15BPK": true,
    "R1PK": true,
    "R5PP": true,
    "R5PPpp": true,
    "R5Ptex": true,
    "RBFK": true,
    "RBFSa": true,
    "RBFSb": false,
    "RBK": true,
    "RBK_L1": true,
    "RBP4E": true,
    "REPHACCOAI": true,
    "RFAMPtex": true,
    "RFAMPtpp": true,
    "RHAT1": false,
    "RHCCE": true,
    "RIBabcpp": true,
    "RIBtex": true,
    "RMI": true,
    "RMK": true,
    "RMNtex": true,
    "RMNtpp": true,
    "RMPA": true,
    "RNDR1": true,
    "RNDR1b": true,
    "RNDR2": true,
    "RNDR2b": true,
    "RNDR3": true,
    "RNDR3b": true,
    "RNDR4": true,
    "RNDR4b": true,
    "RNTR1c2": true,
    "RNTR2c2": true,
    "RNTR3c2": true,
    "RNTR4c2": true,
    "RPE": true,
    "RPI": true,
    "RZ5PP": true,
    "S2FE2SR": true,
    "S2FE2SS": true,
    "S2FE2SS2": true,
    "S2FE2ST": true,
    "S4FE4SR": true,
    "S4FE4ST": true,
    "S7PI": true,
    "SADH": true,
    "SADT2": true,
    "SARCOX": true,
    "SBTPD": true,
    "SBTptspp": true,
    "SBTtex": true,
    "SCYSDS": true,
    "SDPDS": true,
    "SDPTA": true,
    "SELCYSS": true,
    "SELGTHR": true,
    "SELGTHR2": true,
    "SELGTHR3": true,
    "SELNPS": true,
    "SELR": true,
    "SELtex": true,
    "SELtpp": true,
    "SEPHCHCS": true,
    "SERASr": true,
    "SERAT": true,
    "SERD_D": true,
    "SERD_L": true,
    "SERTRS": true,
    "SERTRS2": true,
    "SERt2rpp": true,
    "SERt4pp": true,
    "SERtex": true,
    "SFGTHi": true,
    "SGDS": true,
    "SGSAD": true,
    "SHCHCS3": true,
    "SHCHD2": false,
    "SHCHF": false,
    "SHK3Dr": true,
    "SHKK": false,
    "SHSL1": true,
    "SKMt2pp": true,
    "SKMtex": true,
    "SLNTtex": true,
    "SLNTtpp": true,
    "SO2tex": true,
    "SO2tpp": true,
    "SO3tex": true,
    "SO4t2pp": false,
    "SO4tex": false,
    "SOTA": true,
    "SPMDAT1": true,
    "SPMDAT2": true,
    "SPMDabcpp": true,
    "SPMDt3pp": true,
    "SPMDtex": true,
    "SPMS": false,
    "SPODM": true,
    "SPODMpp": true,
    "SSALx": true,
    "SSALy": true,
    "SUCASPtpp": true,
    "SUCBZL": true,
    "SUCBZS": true,
    "SUCCt2_2pp": true,
    "SUCCt2_3pp": true,
    "SUCCt3pp": true,
    "SUCCtex": true,
    "SUCDi": true,
    "SUCFUMtpp": true,
    "SUCMALtpp": true,
    "SUCOAS": false,
    "SUCRtex": true,
    "SUCTARTtpp": true,
    "SUCptspp": true,
    "SULFACabcpp": true,
    "SULFACtex": true,
    "SULRi": true,
    "SULabcpp": true,
    "T2DECAI": true,
    "TAGURr": true,
    "TALA": true,
    "TARTD": true,
    "TARTRDtex": true,
    "TARTRt7pp": true,
    "TARTRtex": true,
    "TARTt2_3pp": true,
    "TAUDO": true,
    "TAURabcpp": true,
    "TAURtex": true,
    "TCYNTtex": true,
    "TDP": true,
    "TDPADGAT": true,
    "TDPAGTA": true,
    "TDPDRE": true,
    "TDPDRR": true,
    "TDPGDH": true,
    "TDSK": true,
    "TDSR1": true,
    "TDSR2": true,
    "TGBPA": true,
    "THD2pp": true,
    "THDPS": true,
    "THFAT": true,
    "THIORDXi": true,
    "THMDt2pp": true,
    "THMDt2rpp": true,
    "THMDtex": true,
    "THMabcpp": true,
    "THMtex": true,
    "THRA2i": true,
    "THRAi": true,
    "THRD": true,
    "THRD_L": true,
    "THRPtex": true,
    "THRS": true,
    "THRTRS": true,
    "THRabcpp": true,
    "THRt2pp": true,
    "THRt2rpp": false,
    "THRt4pp": true,
    "THRtex": true,
    "THYMt3pp": true,
    "THYMtex": true,
    "THZPSN3": true,
    "TKT1": false,
    "TKT2": true,
    "TMAOR1": true,
    "TMAOR1pp": true,
    "TMAOR2": true,
    "TMAOR2pp": true,
    "TMAOtex": true,
    "TMAtex": true,
    "TMDK1": true,
    "TMDPP": true,
    "TMDS": true,
    "TMK": true,
    "TMPK": true,
    "TMPPP": true,
    "TPI": false,
    "TPRDCOAS": true,
    "TRDR": true,
    "TRE6PH": true,
    "TRE6PP": true,
    "TRE6PS": true,
    "TREH": true,
    "TREHpp": true,
    "TREptspp": true,
    "TREtex": true,
    "TRPAS2": false,
    "TRPS1": true,
    "TRPS2": true,
    "TRPS3": true,
    "TRPTRS": true,
    "TRPt2rpp": true,
    "TRPtex": true,
    "TRSARr": false,
    "TSULabcpp": true,
    "TSULtex": true,
    "TTDCAtexi": true,
    "TTDCEAtexi": true,
    "TTRCYCtex": true,
    "TTRCYCtpp": true,
    "TUNGSabcpp": true,
    "TUNGStex": true,
    "TYMtex": true,
    "TYRL": true,
    "TYROXDApp": true,
    "TYRPpp": true,
    "TYRPtex": true,
    "TYRTA": true,
    "TYRTRS": true,
    "TYRt2rpp": true,
    "TYRtex": true,
    "ThDPAT": true,
    "U23GAAT": false,
    "UAAGDS": false,
    "UACGALPpp": true,
    "UACGAMPpp": true,
    "UACGAMtex": true,
    "UACMAMO": true,
    "UAG2E": true,
    "UAGAAT": false,
    "UAGCVT": true,
    "UAGDP": true,
    "UAGPT3": false,
    "UAMAGS": false,
    "UAMAS": false,
    "UAPGR": true,
    "UDCPDP": true,
    "UDCPDPS": true,
    "UDCPDPpp": true,
    "UDCPPtppi": true,
    "UDPACGALtex": true,
    "UDPG4E": true,
    "UDPGALM": true,
    "UDPGALPpp": true,
    "UDPGALtex": true,
    "UDPGD": true,
    "UDPGDC": true,
    "UDPGLCURtex": true,
    "UDPGPpp": true,
    "UDPGtex": true,
    "UDPKAAT": true,
    "UGLCURPpp": true,
    "UGLT": true,
    "UGLYCH": true,
    "UGMDDS": false,
    "UHGADA": true,
    "ULA4NFT": true,
    "ULA4Ntppi": true,
    "UM3PL": true,
    "UM4PCP": true,
    "UM4PL": true,
    "UMPK": true,
    "UMPtex": true,
    "UPLA4FNF": true,
    "UPLA4FNT": true,
    "UPP3MT": true,
    "UPP3S": true,
    "UPPDC1": true,
    "UPPRT": true,
    "URACPAH": true,
    "URAt2pp": true,
    "URAt2rpp": true,
    "URAtex": true,
    "URDGLYCD": true,
    "UREAtex": true,
    "UREAtpp": true,
    "URIC": true,
    "URIH": true,
    "URIK2": true,
    "URIt2pp": true,
    "URIt2rpp": true,
    "URItex": true,
    "USHD": true,
    "VALTA": true,
    "VALTRS": true,
    "VALabcpp": true,
    "VALt2rpp": true,
    "VALtex": true,
    "VPAMTr": true,
    "WCOS": true,
    "X5PL3E": true,
    "XAND": true,
    "XANt2pp": true,
    "XANtex": true,
    "XANtpp": true,
    "XMPtex": true,
    "XPPT": true,
    "XTSNH": true,
    "XTSNt2rpp": true,
    "XTSNtex": true,
    "XYLI1": true,
    "XYLI2": true,
    "XYLK": true,
    "XYLK2": true,
    "XYLUt2pp": true,
    "XYLUtex": true,
    "XYLabcpp": true,
    "XYLt2pp": true,
    "XYLtex": true,
    "ZN2abcpp": true,
    "ZN2t3pp": true,
    "ZN2tpp": true,
    "ZNabcpp": true,
    "Zn2tex": true
}